investiny/__init__.py
investiny/config.py
investiny/historical.py
investiny/info.py
investiny/py.typed
investiny/search.py
investiny/utils.py
investiny-0.7.1.dist-info/LICENSE
investiny-0.7.1.dist-info/WHEEL
investiny-0.7.1.dist-info/METADATA
investiny-0.7.1.dist-info/RECORD
