Metadata-Version: 2.1
Name: investiny
Version: 0.7.1
Summary: 🤏🏻 `investpy` but made tiny.
Home-page: https://github.com/alvarobartt/investiny
License: MIT
Author: Alvaro Bartolome
Author-email: alvarobartt@yahoo.com
Requires-Python: >=3.8,<4.0
Classifier: License :: OSI Approved :: MIT License
Classifier: Programming Language :: Python :: 3
Classifier: Programming Language :: Python :: 3.8
Classifier: Programming Language :: Python :: 3.9
Classifier: Programming Language :: Python :: 3.10
Classifier: Programming Language :: Python :: 3.11
Provides-Extra: docs
Requires-Dist: httpx (>=0.23.0,<0.24.0)
Requires-Dist: mkdocs (>=1.4.0,<2.0.0); extra == "docs"
Requires-Dist: mkdocs-git-revision-date-localized-plugin (>=1.1.0,<2.0.0); extra == "docs"
Requires-Dist: mkdocs-material (>=8.5.4,<9.0.0); extra == "docs"
Requires-Dist: mkdocstrings[python] (>=0.19.0,<0.20.0); extra == "docs"
Requires-Dist: pydantic (>=1.10.2,<2.0.0)
Project-URL: Documentation, https://github.com/alvarobartt/investiny
Project-URL: Repository, https://investiny.readthedocs.io/
